{"filename":"/home/computer/Github/infinite-devops.github.io/docs/database.json","collections":[{"name":"documents","data":[{"path":"/The infinite devops lifecycle.md","id":0,"type":"child","text":"\n\n\n# The infinite devops lifecycle","name":"The infinite devops lifecycle.md","layout":"post","title":"The infinite devops lifecycle","description":"Out first post :b","category":"devops","tags":"devops","comments":true,"author":"JRichardsz & Bitmanuc","thumbnail_image_url":"https://github.com/infinite-devops/infinite-devops.github.io/assets/3322836/aab5447c-e744-4566-bbbb-9b2b88b212cb","datetime_str":"26 March 2024","datetime":"2024-03-26T00:00:00.000Z","duration":"0:30:20","sounds":{"es":{"type":"vocaroo_url","value":"https://vocaroo.com/embed/1eeVr82U6LCK?autoplay=0"}},"meta":{"revision":0,"created":1713757811626,"version":0},"$loki":1}],"idIndex":null,"binaryIndices":{},"constraints":null,"uniqueNames":[],"transforms":{},"objType":"documents","dirty":false,"cachedIndex":null,"cachedBinaryIndex":null,"cachedData":null,"adaptiveBinaryIndices":true,"transactional":false,"cloneObjects":false,"cloneMethod":"parse-stringify","asyncListeners":false,"disableMeta":false,"disableChangesApi":true,"disableDeltaChangesApi":true,"autoupdate":false,"serializableIndices":true,"disableFreeze":true,"ttl":null,"maxId":1,"DynamicViews":[],"events":{"insert":[],"update":[],"pre-insert":[],"pre-update":[],"close":[],"flushbuffer":[],"error":[],"delete":[null],"warning":[null]},"changes":[],"dirtyIds":[]}],"databaseVersion":1.5,"engineVersion":1.5,"autosave":false,"autosaveInterval":5000,"autosaveHandle":null,"throttledSaves":true,"options":{"serializationMethod":"normal","destructureDelimiter":"$<\n"},"persistenceMethod":"fs","persistenceAdapter":null,"verbose":false,"events":{"init":[null],"loaded":[],"flushChanges":[],"close":[],"changes":[],"warning":[]},"ENV":"NODEJS"}